DjangoKuangjiaJichujiaochengCYuyanBianchengWang/README.md
DjangoKuangjiaJichujiaochengCYuyanBianchengWang/__init__.py
DjangoKuangjiaJichujiaochengCYuyanBianchengWang/__main__.py
DjangoKuangjiaJichujiaochengCYuyanBianchengWang/file.epub
DjangoKuangjiaJichujiaochengCYuyanBianchengWang/index.html
DjangoKuangjiaJichujiaochengCYuyanBianchengWang/css/__init__.py
DjangoKuangjiaJichujiaochengCYuyanBianchengWang/css/annotations.css
DjangoKuangjiaJichujiaochengCYuyanBianchengWang/css/main.css
DjangoKuangjiaJichujiaochengCYuyanBianchengWang/css/normalize.css
DjangoKuangjiaJichujiaochengCYuyanBianchengWang/css/popup.css
DjangoKuangjiaJichujiaochengCYuyanBianchengWang/font/__init__.py
DjangoKuangjiaJichujiaochengCYuyanBianchengWang/font/fontello.eot
DjangoKuangjiaJichujiaochengCYuyanBianchengWang/font/fontello.svg
DjangoKuangjiaJichujiaochengCYuyanBianchengWang/font/fontello.ttf
DjangoKuangjiaJichujiaochengCYuyanBianchengWang/font/fontello.woff
DjangoKuangjiaJichujiaochengCYuyanBianchengWang/img/__init__.py
DjangoKuangjiaJichujiaochengCYuyanBianchengWang/img/annotator-glyph-sprite.png
DjangoKuangjiaJichujiaochengCYuyanBianchengWang/img/annotator-icon-sprite.png
DjangoKuangjiaJichujiaochengCYuyanBianchengWang/img/apple-touch-icon.png
DjangoKuangjiaJichujiaochengCYuyanBianchengWang/img/cancelfullscreen.png
DjangoKuangjiaJichujiaochengCYuyanBianchengWang/img/close.png
DjangoKuangjiaJichujiaochengCYuyanBianchengWang/img/fullscreen.png
DjangoKuangjiaJichujiaochengCYuyanBianchengWang/img/loader.gif
DjangoKuangjiaJichujiaochengCYuyanBianchengWang/img/menu-icon.png
DjangoKuangjiaJichujiaochengCYuyanBianchengWang/img/save.png
DjangoKuangjiaJichujiaochengCYuyanBianchengWang/img/saved.png
DjangoKuangjiaJichujiaochengCYuyanBianchengWang/img/settings-s.png
DjangoKuangjiaJichujiaochengCYuyanBianchengWang/img/settings.png
DjangoKuangjiaJichujiaochengCYuyanBianchengWang/img/star.png
DjangoKuangjiaJichujiaochengCYuyanBianchengWang/js/__init__.py
django_kuangjia_jichujiaocheng_c_yuyan_biancheng_wang-2024.3.5.0.dist-info/METADATA
django_kuangjia_jichujiaocheng_c_yuyan_biancheng_wang-2024.3.5.0.dist-info/WHEEL
django_kuangjia_jichujiaocheng_c_yuyan_biancheng_wang-2024.3.5.0.dist-info/entry_points.txt
django_kuangjia_jichujiaocheng_c_yuyan_biancheng_wang-2024.3.5.0.dist-info/top_level.txt
django_kuangjia_jichujiaocheng_c_yuyan_biancheng_wang-2024.3.5.0.dist-info/RECORD
